{
	"format_version": "1.9.0",
	"credit": "Made with Blockbench",
	"textures": {
		"0": "hunt:block/tablichka",
		"particle": "hunt:block/tablichka"
	},
	"elements": [
		{
			"from": [3.5, 2, 0.2],
			"to": [12.5, 14, 1.2],
			"rotation": {"angle": 22.5, "axis": "x", "origin": [-0.5, 0, 0]},
			"faces": {
				"north": {"uv": [6, 3.5, 9.5, 9.5], "texture": "#0"},
				"east": {"uv": [10.79688, 3.375, 11.29688, 9.375], "texture": "#0"},
				"south": {"uv": [1, 5.5, 5.5, 11.5], "texture": "#0"},
				"west": {"uv": [13, 3.5, 13.5, 9.5], "texture": "#0"},
				"up": {"uv": [14.5, 2.5, 10, 2], "texture": "#0"},
				"down": {"uv": [14.5, 2.5, 10, 3], "texture": "#0"}
			}
		},
		{
			"from": [3.5, -2, 5.2],
			"to": [12.5, 10, 6.2],
			"rotation": {"angle": -22.5, "axis": "x", "origin": [-0.5, 16, 0]},
			"faces": {
				"north": {"uv": [1.60938, 5.375, 6.10938, 11.375], "texture": "#0"},
				"east": {"uv": [11.32813, 4.46875, 11.82813, 10.46875], "texture": "#0"},
				"south": {"uv": [6, 3.5, 9.5, 9.5], "texture": "#0"},
				"west": {"uv": [9.5, 6, 10, 12], "texture": "#0"},
				"up": {"uv": [12.10938, 2.98438, 7.60938, 2.48438], "texture": "#0"},
				"down": {"uv": [14.5, 3.5, 10, 4], "texture": "#0"}
			}
		},
		{
			"from": [3.5, 0, 0.2],
			"to": [5.5, 2, 1.2],
			"rotation": {"angle": 22.5, "axis": "x", "origin": [-0.5, 0, 0]},
			"faces": {
				"north": {"uv": [10, 6, 11, 7], "texture": "#0"},
				"east": {"uv": [7.54688, 10.28125, 8.04688, 11.28125], "texture": "#0"},
				"south": {"uv": [10, 7, 11, 8], "texture": "#0"},
				"west": {"uv": [12, 7.5, 12.5, 8.5], "texture": "#0"},
				"up": {"uv": [9.34375, 11.70313, 8.34375, 11.20313], "texture": "#0"},
				"down": {"uv": [13, 8.5, 12, 9], "texture": "#0"}
			}
		},
		{
			"from": [10.5, 0, 0.2],
			"to": [12.5, 2, 1.2],
			"rotation": {"angle": 22.5, "axis": "x", "origin": [-0.5, 0, 0]},
			"faces": {
				"north": {"uv": [10, 8, 11, 9], "texture": "#0"},
				"east": {"uv": [8.84375, 9.84375, 9.34375, 10.84375], "texture": "#0"},
				"south": {"uv": [10, 9, 11, 10], "texture": "#0"},
				"west": {"uv": [8.96094, 10.375, 9.46094, 11.375], "texture": "#0"},
				"up": {"uv": [10.46094, 10.875, 9.46094, 10.375], "texture": "#0"},
				"down": {"uv": [11.46094, 10.375, 10.46094, 10.875], "texture": "#0"}
			}
		},
		{
			"from": [3.5, -4, 5.2],
			"to": [5.5, -2, 6.2],
			"rotation": {"angle": -22.5, "axis": "x", "origin": [-0.5, 16, 0]},
			"faces": {
				"north": {"uv": [10, 10, 11, 11], "texture": "#0"},
				"east": {"uv": [12, 9.71875, 12.5, 10.71875], "texture": "#0"},
				"south": {"uv": [11, 6, 12, 7], "texture": "#0"},
				"west": {"uv": [5, 5.96875, 5.5, 6.96875], "texture": "#0"},
				"up": {"uv": [5.5625, 10.28125, 4.5625, 9.78125], "texture": "#0"},
				"down": {"uv": [5.14063, 10.53125, 4.14063, 11.03125], "texture": "#0"}
			}
		},
		{
			"from": [10.5, -4, 5.2],
			"to": [12.5, -2, 6.2],
			"rotation": {"angle": -22.5, "axis": "x", "origin": [-0.5, 16, 0]},
			"faces": {
				"north": {"uv": [11, 7, 12, 8], "texture": "#0"},
				"east": {"uv": [4.51563, 8.29688, 5.01563, 9.29688], "texture": "#0"},
				"south": {"uv": [11, 8, 12, 9], "texture": "#0"},
				"west": {"uv": [4.78125, 8.92188, 5.28125, 9.92188], "texture": "#0"},
				"up": {"uv": [6.51563, 8.79688, 5.51563, 8.29688], "texture": "#0"},
				"down": {"uv": [2.375, 6.42188, 1.375, 6.92188], "texture": "#0"}
			}
		},
		{
			"from": [3.5, 14, 0.2],
			"to": [6.5, 14.8, 1.2],
			"rotation": {"angle": 22.5, "axis": "x", "origin": [-0.5, 0, 0]},
			"faces": {
				"north": {"uv": [11, 9, 12.5, 9.5], "texture": "#0"},
				"east": {"uv": [6.23438, 10.71875, 6.73438, 11.21875], "texture": "#0"},
				"south": {"uv": [11, 9.5, 12.5, 10], "texture": "#0"},
				"west": {"uv": [7.3125, 10.71875, 7.8125, 11.21875], "texture": "#0"},
				"up": {"uv": [11.5, 11.5, 10, 11], "texture": "#0"},
				"down": {"uv": [12.5, 10, 11, 10.5], "texture": "#0"}
			}
		},
		{
			"from": [9.5, 14, 0.2],
			"to": [12.5, 14.8, 1.2],
			"rotation": {"angle": 22.5, "axis": "x", "origin": [-0.5, 0, 0]},
			"faces": {
				"north": {"uv": [11, 10.5, 12.5, 11], "texture": "#0"},
				"east": {"uv": [12.5, 7.5, 13, 8], "texture": "#0"},
				"south": {"uv": [10, 11.5, 11.5, 12], "texture": "#0"},
				"west": {"uv": [8, 11, 8.5, 11.5], "texture": "#0"},
				"up": {"uv": [13, 11.5, 11.5, 11], "texture": "#0"},
				"down": {"uv": [13, 11.5, 11.5, 12], "texture": "#0"}
			}
		},
		{
			"from": [9.5, 10, 5.2],
			"to": [12.5, 10.8, 6.2],
			"rotation": {"angle": -22.5, "axis": "x", "origin": [-0.5, 16, 0]},
			"faces": {
				"north": {"uv": [3.4375, 9.14063, 4.9375, 9.64063], "texture": "#0"},
				"east": {"uv": [12.5, 8, 13, 8.5], "texture": "#0"},
				"south": {"uv": [4.9375, 9.14063, 6.4375, 9.64063], "texture": "#0"},
				"west": {"uv": [8.76563, 11.3125, 9.26563, 11.8125], "texture": "#0"},
				"up": {"uv": [6.875, 10.26563, 5.375, 9.76563], "texture": "#0"},
				"down": {"uv": [9.07813, 5.20313, 7.57813, 5.70313], "texture": "#0"}
			}
		},
		{
			"from": [3.5, 10, 5.2],
			"to": [6.5, 10.8, 6.2],
			"rotation": {"angle": -22.5, "axis": "x", "origin": [-0.5, 16, 0]},
			"faces": {
				"north": {"uv": [6, 12, 7.5, 12.5], "texture": "#0"},
				"east": {"uv": [12.5, 9, 13, 9.5], "texture": "#0"},
				"south": {"uv": [12, 6, 13.5, 6.5], "texture": "#0"},
				"west": {"uv": [12.5, 9.5, 13, 10], "texture": "#0"},
				"up": {"uv": [13.5, 7, 12, 6.5], "texture": "#0"},
				"down": {"uv": [13.5, 7, 12, 7.5], "texture": "#0"}
			}
		},
		{
			"from": [3.5, 14.8, 0.2],
			"to": [12.5, 15.8, 1.2],
			"rotation": {"angle": 22.5, "axis": "x", "origin": [-0.5, 0, 0]},
			"faces": {
				"north": {"uv": [10, 4, 14.5, 4.5], "texture": "#0"},
				"east": {"uv": [10.0625, 11.45313, 10.5625, 11.95313], "texture": "#0"},
				"south": {"uv": [10, 4.5, 14.5, 5], "texture": "#0"},
				"west": {"uv": [12.5, 10, 13, 10.5], "texture": "#0"},
				"up": {"uv": [14.5, 5.5, 10, 5], "texture": "#0"},
				"down": {"uv": [14.5, 5.5, 10, 6], "texture": "#0"}
			}
		},
		{
			"from": [3.5, 10.8, 5.2],
			"to": [12.5, 11.8, 6.2],
			"rotation": {"angle": -22.5, "axis": "x", "origin": [-0.5, 16, 0]},
			"faces": {
				"north": {"uv": [5.45313, 9.32813, 9.95313, 9.82813], "texture": "#0"},
				"east": {"uv": [8.09375, 8.34375, 8.59375, 8.84375], "texture": "#0"},
				"south": {"uv": [7.90625, 10.59375, 12.40625, 11.09375], "texture": "#0"},
				"west": {"uv": [7.25, 8.125, 7.75, 8.625], "texture": "#0"},
				"up": {"uv": [11.46875, 9.57813, 6.96875, 9.07813], "texture": "#0"},
				"down": {"uv": [13.375, 7.09375, 8.875, 7.59375], "texture": "#0"}
			}
		}
	],
	"display": {},
	"groups": [
		{
			"name": "group",
			"origin": [-0.5, 0, 0],
			"color": 0,
			"children": [0, 1, 2, 3, 4, 5, 6, 7, 8, 9, 10, 11]
		}
	]
}